make_prg/__init__.py
make_prg/__main__.py
make_prg/from_msa/__init__.py
make_prg/from_msa/cluster_sequences.py
make_prg/from_msa/interval_partition.py
make_prg/prg_builder.py
make_prg/recursion_tree.py
make_prg/subcommands/__init__.py
make_prg/subcommands/from_msa.py
make_prg/subcommands/output_type.py
make_prg/subcommands/update.py
make_prg/update/MLPath.py
make_prg/update/__init__.py
make_prg/update/denovo_variants.py
make_prg/update/update_shared_data.py
make_prg/utils/__init__.py
make_prg/utils/gfa.py
make_prg/utils/input_output_files.py
make_prg/utils/io_utils.py
make_prg/utils/mafft-linux64/mafft.bat
make_prg/utils/mafft-linux64/mafftdir/bin/mafft
make_prg/utils/mafft-linux64/mafftdir/libexec/addsingle
make_prg/utils/mafft-linux64/mafftdir/libexec/contrafoldwrap
make_prg/utils/mafft-linux64/mafftdir/libexec/countlen
make_prg/utils/mafft-linux64/mafftdir/libexec/dash_alignments
make_prg/utils/mafft-linux64/mafftdir/libexec/dash_client
make_prg/utils/mafft-linux64/mafftdir/libexec/dash_sequences.fa
make_prg/utils/mafft-linux64/mafftdir/libexec/disttbfast
make_prg/utils/mafft-linux64/mafftdir/libexec/dndblast
make_prg/utils/mafft-linux64/mafftdir/libexec/dndfast7
make_prg/utils/mafft-linux64/mafftdir/libexec/dndpre
make_prg/utils/mafft-linux64/mafftdir/libexec/dvtditr
make_prg/utils/mafft-linux64/mafftdir/libexec/f2cl
make_prg/utils/mafft-linux64/mafftdir/libexec/filter
make_prg/utils/mafft-linux64/mafftdir/libexec/getlag
make_prg/utils/mafft-linux64/mafftdir/libexec/hat3
make_prg/utils/mafft-linux64/mafftdir/libexec/hex2maffttext
make_prg/utils/mafft-linux64/mafftdir/libexec/mafft-distance
make_prg/utils/mafft-linux64/mafftdir/libexec/mafft-homologs.1
make_prg/utils/mafft-linux64/mafftdir/libexec/mafft-profile
make_prg/utils/mafft-linux64/mafftdir/libexec/mafft.1
make_prg/utils/mafft-linux64/mafftdir/libexec/mafftash_premafft.pl
make_prg/utils/mafft-linux64/mafftdir/libexec/maffttext2hex
make_prg/utils/mafft-linux64/mafftdir/libexec/makedirectionlist
make_prg-0.5.0.dist-info/entry_points.txt
make_prg-0.5.0.dist-info/LICENSE
make_prg-0.5.0.dist-info/WHEEL
make_prg-0.5.0.dist-info/METADATA
make_prg-0.5.0.dist-info/RECORD
