Metadata-Version: 2.1
Name: make-prg
Version: 0.5.0
Summary: Code to create a PRG from a Multiple Sequence Alignment file
Home-page: https://github.com/iqbal-lab-org/make_prg
License: MIT
Keywords: python,reference-graph,genome-graph,bioinformatics
Author: Michael Hall
Author-email: michael@mbh.sh
Requires-Python: >=3.8,<=3.11
Classifier: License :: OSI Approved :: MIT License
Classifier: Programming Language :: Python :: 3
Classifier: Programming Language :: Python :: 3.8
Classifier: Programming Language :: Python :: 3.9
Classifier: Programming Language :: Python :: 3.10
Classifier: Programming Language :: Python :: 3.11
Provides-Extra: debug-graphs
Provides-Extra: precompiled-binary
Requires-Dist: biopython (==1.79)
Requires-Dist: intervaltree (>=3.1.0,<4.0.0)
Requires-Dist: loguru (>=0.6.0,<0.7.0)
Requires-Dist: matplotlib (>=3.5.0,<4.0.0); extra == "debug-graphs" or extra == "precompiled-binary"
Requires-Dist: networkx (>=2.6.3,<3.0.0); extra == "debug-graphs" or extra == "precompiled-binary"
Requires-Dist: numpy (>=1.24.4,<2.0.0)
Requires-Dist: pygraphviz (==1.7); extra == "debug-graphs" or extra == "precompiled-binary"
Requires-Dist: pyinstaller (>=5.6,<6.0); extra == "precompiled-binary"
Requires-Dist: scikit-learn (>=1.3.0,<2.0.0)
Requires-Dist: setuptools (>=65,<66)
Project-URL: Documentation, https://github.com/iqbal-lab-org/make_prg
Project-URL: Repository, https://github.com/iqbal-lab-org/make_prg
